titanic_pp_py-0.0.7.dist-info/METADATA
titanic_pp_py-0.0.7.dist-info/WHEEL
titanic_pp_py-0.0.7.dist-info/licenses/LICENSE
titanic_pp_py/__init__.py
titanic_pp_py/__init__.pyi
titanic_pp_py/py.typed
titanic_pp_py/titanic_pp_py.cp311-win_amd64.pyd
titanic_pp_py-0.0.7.dist-info/RECORD
