Metadata-Version: 2.3
Name: titanic-pp-py
Version: 0.0.7
Classifier: Development Status :: 4 - Beta
Classifier: Intended Audience :: Developers
Classifier: License :: OSI Approved :: MIT License
Classifier: Operating System :: OS Independent
Classifier: Programming Language :: Rust
Classifier: Programming Language :: Python :: Implementation :: CPython
Classifier: Programming Language :: Python :: Implementation :: PyPy
License-File: LICENSE
Summary: osu! difficulty and pp calculation for all modes
Keywords: osu,pp,stars,performance,difficulty
Author: Max Ohn <ohn.m@hotmail.de>, tsunyoku <tsunyoku@gmail.com>, Lekuruu <contact@lekuru.xyz>, kanaarima <akataltosu@gmail.com>
Author-email: Max Ohn <ohn.m@hotmail.de>, tsunyoku <tsunyoku@gmail.com>, Lekuruu <contact@lekuru.xyz>, kanaarima <akataltosu@gmail.com>
License: MIT
Requires-Python: >=3.7
Project-URL: repository, https://github.com/osuTitanic/titanic-pp-py
